pyvdk/__init__.py
pyvdk/api/__init__.py
pyvdk/api/abc.py
pyvdk/api/api.py
pyvdk/api/categories/__init__.py
pyvdk/api/categories/account.py
pyvdk/api/categories/ads.py
pyvdk/api/categories/app_widgets.py
pyvdk/api/categories/apps.py
pyvdk/api/categories/auth.py
pyvdk/api/categories/board.py
pyvdk/api/categories/database.py
pyvdk/api/categories/docs.py
pyvdk/api/categories/downloaded_games.py
pyvdk/api/categories/fave.py
pyvdk/api/categories/friends.py
pyvdk/api/categories/gifts.py
pyvdk/api/categories/groups.py
pyvdk/api/categories/leads.py
pyvdk/api/categories/likes.py
pyvdk/api/categories/market.py
pyvdk/api/categories/messages.py
pyvdk/api/categories/newsfeed.py
pyvdk/api/categories/notes.py
pyvdk/api/categories/notifications.py
pyvdk/api/categories/orders.py
pyvdk/api/categories/pages.py
pyvdk/api/categories/photos.py
pyvdk/api/categories/polls.py
pyvdk/api/categories/pretty_cards.py
pyvdk/api/categories/search.py
pyvdk/api/categories/secure.py
pyvdk/api/categories/stats.py
pyvdk/api/categories/status.py
pyvdk/api/categories/storage.py
pyvdk/api/categories/stories.py
pyvdk/api/categories/streaming.py
pyvdk/api/categories/users.py
pyvdk/api/categories/utils.py
pyvdk/api/categories/video.py
pyvdk/api/categories/wall.py
pyvdk/api/categories/widgets.py
pyvdk/api/category.py
pyvdk/bot.py
pyvdk/config.py
pyvdk/event/__init__.py
pyvdk/event/abc.py
pyvdk/event/event_types.py
pyvdk/event/handler.py
pyvdk/event/labeler.py
pyvdk/event/view.py
pyvdk/logging.py
pyvdk/rules/__init__.py
pyvdk/rules/abc.py
pyvdk/rules/bunch.py
pyvdk/rules/rules.py
pyvdk/tools/__init__.py
pyvdk/tools/funcs.py
pyvdk/tools/keyboard/__init__.py
pyvdk/tools/keyboard/abc.py
pyvdk/tools/keyboard/buttons.py
pyvdk/tools/keyboard/keyboard.py
pyvdk/tools/logger.py
pyvdk/tools/mention.py
pyvdk/types/__init__.py
pyvdk/types/abc.py
pyvdk/types/custom.py
pyvdk/types/group_events.py
pyvdk/types/objects.py
pyvdk/utils.py
pyvdk-0.0.3.3.dist-info/LICENSE
pyvdk-0.0.3.3.dist-info/WHEEL
pyvdk-0.0.3.3.dist-info/METADATA
pyvdk-0.0.3.3.dist-info/RECORD
